virus/__init__.py
virus/__main__.py
virus/functions.py
VirusPrank-1.0.0.dist-info/LICENSE
VirusPrank-1.0.0.dist-info/METADATA
VirusPrank-1.0.0.dist-info/WHEEL
VirusPrank-1.0.0.dist-info/entry_points.txt
VirusPrank-1.0.0.dist-info/top_level.txt
VirusPrank-1.0.0.dist-info/RECORD
