Metadata-Version: 2.1
Name: VirusPrank
Version: 1.0.0
Summary: Harmless virus prank
Home-page: UNKNOWN
Author: Dev Shah
Author-email: dgm82832@gmail.com
License: MIT
Platform: UNKNOWN
Classifier: License :: OSI Approved :: MIT License
Classifier: Programming Language :: Python :: 3.7
Classifier: Programming Language :: Python :: 3.8
